thousandeyes_sdk/credentials/__init__.py
thousandeyes_sdk/credentials/py.typed
thousandeyes_sdk/credentials/api/__init__.py
thousandeyes_sdk/credentials/api/credentials_api.py
thousandeyes_sdk/credentials/models/__init__.py
thousandeyes_sdk/credentials/models/credential.py
thousandeyes_sdk/credentials/models/credential_request.py
thousandeyes_sdk/credentials/models/credential_without_value.py
thousandeyes_sdk/credentials/models/credentials.py
thousandeyes_sdk/credentials/models/error.py
thousandeyes_sdk/credentials/models/link.py
thousandeyes_sdk/credentials/models/self_links.py
thousandeyes_sdk/credentials/models/unauthorized_error.py
thousandeyes_sdk/credentials/models/validation_error.py
thousandeyes_sdk/credentials/models/validation_error_item.py
thousandeyes_sdk_credentials-2.23.0.dist-info/licenses/LICENSE
thousandeyes_sdk_credentials-2.23.0.dist-info/licenses/NOTICE
thousandeyes_sdk_credentials-2.23.0.dist-info/METADATA
thousandeyes_sdk_credentials-2.23.0.dist-info/WHEEL
thousandeyes_sdk_credentials-2.23.0.dist-info/top_level.txt
thousandeyes_sdk_credentials-2.23.0.dist-info/RECORD
